{"cameraMode":{"drawMode":0,"name":"Shaded","section":"Shading Mode"},"sceneLighting":true,"audioPlay":false,"sceneViewState":{"showFog":true,"showMaterialUpdate":false,"showSkybox":true,"showFlares":true,"showImageEffects":true,"showParticleSystems":true,"showVisualEffectGraphs":true,"m_FxEnabled":true},"in2DMode":false,"pivot":{"x":-6858.4375,"y":-14531.38671875,"z":3462.529052734375},"rotation":{"x":-0.42182600498199465,"y":0.47131675481796267,"z":-0.27451786398887637,"w":-0.7242693305015564},"size":10893.3671875,"orthographic":false}